agno/__init__.py
agno/py.typed
agno_os-0.1.0.dist-info/licenses/LICENSE
agno_os-0.1.0.dist-info/METADATA
agno_os-0.1.0.dist-info/WHEEL
agno_os-0.1.0.dist-info/top_level.txt
agno_os-0.1.0.dist-info/RECORD
