Metadata-Version: 2.4
Name: agno-os
Version: 0.1.0
Summary: A lightweight framework building Agentic Systems
Author-email: Agno Team <support@agno.com>
License: Copyright (c) Agno, Inc.
Requires-Python: <4,>=3.7
License-File: LICENSE
Dynamic: license-file
